license_manager/__init__.py
license_manager/core.py
tests/__init__.py
tests/test_core.py
license_manager_py-0.0.2.dist-info/LICENSE
license_manager_py-0.0.2.dist-info/METADATA
license_manager_py-0.0.2.dist-info/WHEEL
license_manager_py-0.0.2.dist-info/top_level.txt
license_manager_py-0.0.2.dist-info/RECORD
