Metadata-Version: 2.1
Name: license-manager-py
Version: 0.0.2
Summary: A comprehensive license management module
Home-page: https://github.com/shully/license-manager
Author: Your Name
Author-email: a330289953@gmail.com
Keywords: license management,licensing
Classifier: Development Status :: 3 - Alpha
Classifier: Intended Audience :: Developers
Classifier: License :: OSI Approved :: MIT License
Classifier: Programming Language :: Python :: 3.12
Requires-Python: >=3.7
License-File: LICENSE
Requires-Dist: cryptography>=3.4.7
